[
    {
        "title": "x + 15 = 25",
        "options": [
            "10",
            "15",
            "20",
            "25",
            "30"
        ],
        "answer": 1
    },
    {
        "title": "x + 9 = 14",
        "options": [
            "3",
            "4",
            "5",
            "6",
            "7"
        ],
        "answer": 0
    },
    {
        "title": "x + 8 = 15",
        "options": [
            "5",
            "6",
            "7",
            "8",
            "9"
        ],
        "answer": 2
    },
    {
        "title": "x + 4 = 10",
        "options": [
            "4",
            "5",
            "6",
            "7",
            "8"
        ],
        "answer": 1
    },
    {
        "title": "x + 3 = 15",
        "options": [
            "10",
            "11",
            "12",
            "13",
            "14"
        ],
        "answer": 0
    },
    {
        "title": "x + 11 = 16",
        "options": [
            "4",
            "5",
            "6",
            "7",
            "8"
        ],
        "answer": 1
    },
    {
        "title": "x + 9 = 18",
        "options": [
            "8",
            "9",
            "10",
            "11",
            "12"
        ],
        "answer": 0
    },
    {
        "title": "x + 7 = 10",
        "options": [
            "2",
            "3",
            "4",
            "5",
            "6"
        ],
        "answer": 0
    },
    {
        "title": "x + 5 = 7",
        "options": [
            "1",
            "2",
            "3",
            "4",
            "5"
        ],
        "answer": 0
    },
    {
        "title": "x + 6 = 12",
        "options": [
            "5",
            "6",
            "7",
            "8",
            "9"
        ],
        "answer": 0
    },
    {
        "title": "x + 2 = 10",
        "options": [
            "7",
            "8",
            "9",
            "10",
            "11"
        ],
        "answer": 0
    },
    {
        "title": "x + 3 = 13",
        "options": [
            "9",
            "10",
            "11",
            "12",
            "13"
        ],
        "answer": 0
    },
    {
        "title": "x + 5 = 15",
        "options": [
            "9",
            "10",
            "11",
            "12",
            "13"
        ],
        "answer": 1
    },
    {
        "title": "x + 7 = 12",
        "options": [
            "4",
            "5",
            "6",
            "7",
            "8"
        ],
        "answer": 0
    },
    {
        "title": "x + 6 = 18",
        "options": [
            "12",
            "13",
            "14",
            "15",
            "16"
        ],
        "answer": 0
    },
    {
        "title": "x + 4 = 19",
        "options": [
            "14",
            "15",
            "16",
            "17",
            "18"
        ],
        "answer": 0
    },
    {
        "title": "x + 5 = 10",
        "options": [
            "4",
            "5",
            "6",
            "7",
            "8"
        ],
        "answer": 1
    },
    {
        "title": "x + 14 = 20",
        "options": [
            "5",
            "6",
            "7",
            "8",
            "9"
        ],
        "answer": 0
    },
    {
        "title": "x + 3 = 17",
        "options": [
            "13",
            "14",
            "15",
            "16",
            "17"
        ],
        "answer": 0
    },

    {
        "title": "x + x = 10",
        "options": [
            "5",
            "10",
            "20",
            "30",
            "40"
        ],
        "answer": 0
    }

]
